{"cameraMode":{"drawMode":0,"name":"Shaded","section":"Shading Mode"},"sceneLighting":false,"audioPlay":false,"sceneViewState":{"m_AlwaysRefresh":false,"showFog":true,"showSkybox":false,"showFlares":true,"showImageEffects":true,"showParticleSystems":true,"showVisualEffectGraphs":true,"m_FxEnabled":true},"in2DMode":false,"pivot":{"x":8.13509464263916,"y":17.374862670898439,"z":74.0865707397461},"rotation":{"x":0.07146195322275162,"y":-0.06817774474620819,"z":-0.004890641663223505,"w":-0.9951107501983643},"size":47.53896713256836,"orthographic":false}